MANIFEST.in
requirements.txt
setup.py
test_requirements.txt
version.txt
cloudshell/__init__.py
cloudshell/firewall/__init__.py
cloudshell/firewall/firewall_resource_driver_interface.py
cloudshell/firewall/generic_bootstrap.py
cloudshell/firewall/networking_utils.py
cloudshell/firewall/autoload/__init__.py
cloudshell/firewall/autoload/firewall_attributes.py
cloudshell/firewall/autoload/firewall_autoload_resource_attributes.py
cloudshell/firewall/autoload/firewall_autoload_resource_structure.py
cloudshell/firewall/autoload/firewall_model.py
cloudshell/firewall/autoload/model/__init__.py
cloudshell/firewall/autoload/model/attribute_container.py
cloudshell/firewall/autoload/model/generic_resource.py
cloudshell/firewall/operations/__init__.py
cloudshell/firewall/operations/interfaces/__init__.py
cloudshell/firewall/operations/interfaces/autoload_operations_interface.py
cloudshell/firewall/operations/interfaces/configuration_operations_interface.py
cloudshell/firewall/operations/interfaces/firmware_operations_interface.py
cloudshell/firewall/operations/interfaces/power_operations_interface.py
cloudshell/firewall/operations/interfaces/send_command_interface.py
cloudshell_firewall_core.egg-info/PKG-INFO
cloudshell_firewall_core.egg-info/SOURCES.txt
cloudshell_firewall_core.egg-info/dependency_links.txt
cloudshell_firewall_core.egg-info/requires.txt
cloudshell_firewall_core.egg-info/top_level.txt