Metadata-Version: 1.0
Name: cloudshell-firewall-core
Version: 1.0.8
Summary: QualiSystems Firewall Python package
Home-page: http://www.qualisystems.com/
Author: QualiSystems
Author-email: info@qualisystems.com
License: UNKNOWN
Platform: UNKNOWN
